PlayerLibrary/__init__.py
PlayerLibrary/api_handler.py
PlayerLibrary/base_context.py
PlayerLibrary/browser_handler.py
PlayerLibrary/button_handler.py
PlayerLibrary/checkbox_handler.py
PlayerLibrary/custom_locator.py
PlayerLibrary/datepicker_handler.py
PlayerLibrary/dropdown_handler.py
PlayerLibrary/element_handler.py
PlayerLibrary/iframe_handler.py
PlayerLibrary/page_handler.py
PlayerLibrary/table_handler.py
PlayerLibrary/textbox_handler.py
PlayerLibrary/utils.py
robotframework_playerlibrary-1.1.0.dist-info/LICENSE
robotframework_playerlibrary-1.1.0.dist-info/METADATA
robotframework_playerlibrary-1.1.0.dist-info/WHEEL
robotframework_playerlibrary-1.1.0.dist-info/top_level.txt
robotframework_playerlibrary-1.1.0.dist-info/RECORD
